{
  "$schema": "https://developer.microsoft.com/json-schemas/fabric/item/report/definition/visualContainer/2.9.0/schema.json",
  "name": "access_detail",
  "position": {
    "x": 204,
    "y": 458,
    "z": 303,
    "height": 234,
    "width": 680,
    "tabOrder": 303
  },
  "visual": {
    "visualType": "tableEx",
    "query": {
      "queryState": {
        "Values": {
          "projections": [
            {
              "field": {
                "Column": {
                  "Expression": {
                    "SourceRef": {
                      "Entity": "DimReport"
                    }
                  },
                  "Property": "ReportName"
                }
              },
              "queryRef": "DimReport.ReportName",
              "displayName": "ReportName"
            },
            {
              "field": {
                "Column": {
                  "Expression": {
                    "SourceRef": {
                      "Entity": "DimReport"
                    }
                  },
                  "Property": "ReportTier"
                }
              },
              "queryRef": "DimReport.ReportTier",
              "displayName": "Tier"
            },
            {
              "field": {
                "Column": {
                  "Expression": {
                    "SourceRef": {
                      "Entity": "DimReport"
                    }
                  },
                  "Property": "SensitivityLabel"
                }
              },
              "queryRef": "DimReport.SensitivityLabel",
              "displayName": "Sensitivity"
            },
            {
              "field": {
                "Measure": {
                  "Expression": {
                    "SourceRef": {
                      "Entity": "KPI Measures"
                    }
                  },
                  "Property": "RLS Exceptions"
                }
              },
              "queryRef": "KPI Measures.RLS Exceptions",
              "displayName": "RLS Exceptions"
            },
            {
              "field": {
                "Measure": {
                  "Expression": {
                    "SourceRef": {
                      "Entity": "KPI Measures"
                    }
                  },
                  "Property": "Pending Access Reviews"
                }
              },
              "queryRef": "KPI Measures.Pending Access Reviews",
              "displayName": "Pending Access Reviews"
            },
            {
              "field": {
                "Measure": {
                  "Expression": {
                    "SourceRef": {
                      "Entity": "KPI Measures"
                    }
                  },
                  "Property": "Deployment Control Score"
                }
              },
              "queryRef": "KPI Measures.Deployment Control Score",
              "displayName": "Control Score"
            }
          ]
        }
      },
      "sortDefinition": {
        "sort": [
          {
            "field": {
              "Measure": {
                "Expression": {
                  "SourceRef": {
                    "Entity": "KPI Measures"
                  }
                },
                "Property": "RLS Exceptions"
              }
            },
            "direction": "Descending"
          }
        ],
        "isDefaultSort": true
      }
    },
    "visualContainerObjects": {
      "general": [
        {
          "properties": {
            "altText": {
              "expr": {
                "Literal": {
                  "Value": "'Shows filtered dashboard evidence for Access Review Detail.'"
                }
              }
            }
          }
        }
      ],
      "title": [
        {
          "properties": {
            "show": {
              "expr": {
                "Literal": {
                  "Value": "true"
                }
              }
            },
            "text": {
              "expr": {
                "Literal": {
                  "Value": "'Access Review Detail'"
                }
              }
            },
            "fontColor": {
              "solid": {
                "color": {
                  "expr": {
                    "Literal": {
                      "Value": "'#13212B'"
                    }
                  }
                }
              }
            },
            "fontSize": {
              "expr": {
                "Literal": {
                  "Value": "9L"
                }
              }
            },
            "bold": {
              "expr": {
                "Literal": {
                  "Value": "true"
                }
              }
            },
            "titleWrap": {
              "expr": {
                "Literal": {
                  "Value": "true"
                }
              }
            }
          }
        }
      ],
      "background": [
        {
          "properties": {
            "show": {
              "expr": {
                "Literal": {
                  "Value": "true"
                }
              }
            },
            "color": {
              "solid": {
                "color": {
                  "expr": {
                    "Literal": {
                      "Value": "'#FFFFFF'"
                    }
                  }
                }
              }
            },
            "transparency": {
              "expr": {
                "Literal": {
                  "Value": "0L"
                }
              }
            }
          }
        }
      ],
      "border": [
        {
          "properties": {
            "show": {
              "expr": {
                "Literal": {
                  "Value": "true"
                }
              }
            },
            "color": {
              "solid": {
                "color": {
                  "expr": {
                    "Literal": {
                      "Value": "'#D8E5E8'"
                    }
                  }
                }
              }
            },
            "radius": {
              "expr": {
                "Literal": {
                  "Value": "8L"
                }
              }
            }
          }
        }
      ],
      "visualHeader": [
        {
          "properties": {
            "show": {
              "expr": {
                "Literal": {
                  "Value": "false"
                }
              }
            }
          }
        }
      ]
    }
  }
}