{
  "objects": {
    "valueAxis": [
      {
        "properties": {
          "showAxisTitle": {
            "expr": {
              "Literal": {
                "Value": "false"
              }
            }
          },
          "gridlineShow": {
            "expr": {
              "Literal": {
                "Value": "false"
              }
            }
          }
        }
      }
    ],
    "categoryAxis": [
      {
        "properties": {
          "showAxisTitle": {
            "expr": {
              "Literal": {
                "Value": "false"
              }
            }
          },
          "gridlineShow": {
            "expr": {
              "Literal": {
                "Value": "false"
              }
            }
          },
          "concatenateLabels": {
            "expr": {
              "Literal": {
                "Value": "false"
              }
            }
          }
        }
      }
    ],
    "labels": [
      {
        "properties": {
          "show": {
            "expr": {
              "Literal": {
                "Value": "true"
              }
            }
          },
          "labelDisplayUnits": {
            "expr": {
              "Literal": {
                "Value": "1000000.0D"
              }
            }
          }
        }
      }
    ],
    "legend": [
      {
        "properties": {
          "showTitle": {
            "expr": {
              "Literal": {
                "Value": "false"
              }
            }
          },
          "position": {
            "expr": {
              "Literal": {
                "Value": "'Top'"
              }
            }
          }
        }
      }
    ],
    "dataPoint": [
      {
        "properties": {
          "fill": {
            "solid": {
              "color": {
                "expr": {
                  "Literal": {
                    "Value": "'#D45D5D'"
                  }
                }
              }
            }
          }
        },
        "selector": {
          "metadata": "KPI Measures.Expected Loss"
        }
      }
    ]
  },
  "projectionOrdering": {
    "Category": [
      0
    ],
    "Y": [
      1
    ]
  },
  "queryMetadata": {
    "Select": [
      {
        "Restatement": "Merchant category",
        "Name": "DimMerchant.merchant_category",
        "Type": 2048
      },
      {
        "Restatement": "Expected loss",
        "Name": "KPI Measures.Expected Loss",
        "Type": 1,
        "Format": "$#,0,,.0M"
      }
    ]
  },
  "visualElements": [
    {
      "DataRoles": [
        {
          "Name": "Category",
          "Projection": 0,
          "isActive": true
        },
        {
          "Name": "Y",
          "Projection": 1,
          "isActive": false
        }
      ]
    }
  ],
  "selects": [
    {
      "displayName": "Merchant category",
      "queryName": "DimMerchant.merchant_category",
      "roles": {
        "Category": true
      },
      "type": {
        "category": null,
        "underlyingType": 1
      },
      "expr": {
        "Column": {
          "Expression": {
            "SourceRef": {
              "Entity": "DimMerchant"
            }
          },
          "Property": "merchant_category"
        }
      }
    },
    {
      "displayName": "Expected loss",
      "queryName": "KPI Measures.Expected Loss",
      "roles": {
        "Y": true
      },
      "type": {
        "category": null,
        "underlyingType": 259
      },
      "expr": {
        "Measure": {
          "Expression": {
            "SourceRef": {
              "Entity": "KPI Measures"
            }
          },
          "Property": "Expected Loss"
        }
      },
      "format": "$#,0,,.0M"
    }
  ],
  "projectionActiveItems": {
    "Category": [
      {
        "queryRef": "DimMerchant.merchant_category",
        "suppressConcat": false
      }
    ]
  }
}